tempocnn/__init__.py
tempocnn/classifier.py
tempocnn/commands.py
tempocnn/feature.py
tempocnn/version.py
tempocnn/models/cnn.h5
tempocnn/models/deepsquare_k1.h5
tempocnn/models/deepsquare_k2.h5
tempocnn/models/deepsquare_k4.h5
tempocnn/models/deepsquare_k8.h5
tempocnn/models/deeptemp_k2.h5
tempocnn/models/deeptemp_k4.h5
tempocnn/models/deeptemp_k8.h5
tempocnn/models/dt_maz_m_fold0.h5
tempocnn/models/dt_maz_m_fold1.h5
tempocnn/models/dt_maz_m_fold2.h5
tempocnn/models/dt_maz_m_fold3.h5
tempocnn/models/dt_maz_m_fold4.h5
tempocnn/models/dt_maz_v_fold0.h5
tempocnn/models/dt_maz_v_fold1.h5
tempocnn/models/dt_maz_v_fold2.h5
tempocnn/models/dt_maz_v_fold3.h5
tempocnn/models/dt_maz_v_fold4.h5
tempocnn/models/fcn.h5
tempocnn/models/ismir2018.h5
tempocnn/models/shallowtemp_k1.h5
tempocnn/models/shallowtemp_k2.h5
tempocnn/models/shallowtemp_k4.h5
tempocnn/models/shallowtemp_k6.h5
tempocnn-0.0.8.dist-info/LICENSE
tempocnn-0.0.8.dist-info/METADATA
tempocnn-0.0.8.dist-info/WHEEL
tempocnn-0.0.8.dist-info/entry_points.txt
tempocnn-0.0.8.dist-info/top_level.txt
tempocnn-0.0.8.dist-info/RECORD
