Metadata-Version: 2.1
Name: tempocnn
Version: 0.0.8
Summary: Python audio signal processing library for musical tempo detection
Home-page: https://github.com/hendriks73/tempo-cnn
Author: Hendrik Schreiber tagtraum industries incorporated, Raleigh, NC, USA
Author-email: hs@tagtraum.com
License: AGPL
Classifier: Development Status :: 3 - Alpha
Classifier: Programming Language :: Python :: 3.9
Classifier: Programming Language :: Python :: 3.10
Classifier: Programming Language :: Python :: 3.11
Classifier: Environment :: Console
Classifier: License :: OSI Approved :: GNU Affero General Public License v3
Classifier: Topic :: Multimedia :: Sound/Audio :: Analysis
Classifier: Topic :: Scientific/Engineering :: Artificial Intelligence
Requires-Python: >=3.9,<3.12
License-File: LICENSE
Requires-Dist: jams>=0.3.1
Requires-Dist: librosa>=0.9.0
Requires-Dist: matplotlib>=3.0.0
Requires-Dist: scipy>=1.10.0
Requires-Dist: setuptools>=65.5.1
Requires-Dist: tensorflow==2.17.0
Provides-Extra: testing
Requires-Dist: pytest; extra == "testing"
Requires-Dist: coverage; extra == "testing"
Requires-Dist: pytest-console-scripts; extra == "testing"
